{
    "provider_url": "https://mmyykkee.github.io", 
    "description": "To develop and implement successful solutions to provide top quality and affordable healthcare to the people of Nairobi and Kenya at large and concentrate all our activities on the need of our patient. Strive for excellence in a unique brand of patient care delivered by people who are passionate about life, personal respect and dignity.", 
    "title": "Nimoli Medical Services", 
    "url": "https://mmyykkee.github.io/nimoli-web.github.io/", 
    "thumbnail_width": 820, 
    "thumbnail_url": "https://mmyykkee.github.io/nimoli-web.github.io/Images/Final%20Nimoli%20Logo%202.jpg", 
    "version": "1.0", 
    "provider_name": "Mmyykkee", 
    "type": "link", 
    "thumbnail_height": 768
}